dvg_pyqtgraph_threadsafe.py
dvg_pyqtgraph_threadsafe-3.4.0.dist-info/AUTHORS.rst
dvg_pyqtgraph_threadsafe-3.4.0.dist-info/LICENSE.txt
dvg_pyqtgraph_threadsafe-3.4.0.dist-info/METADATA
dvg_pyqtgraph_threadsafe-3.4.0.dist-info/WHEEL
dvg_pyqtgraph_threadsafe-3.4.0.dist-info/top_level.txt
dvg_pyqtgraph_threadsafe-3.4.0.dist-info/RECORD
