Metadata-Version: 2.1
Name: dvg-pyqtgraph-threadsafe
Version: 3.4.0
Summary: PyQtGraph library providing thread-safe plot curves with underlying (ring) buffers.
Home-page: https://github.com/Dennis-van-Gils/python-dvg-pyqtgraph-threadsafe
Author: Dennis van Gils
Author-email: vangils.dennis@gmail.com
License: MIT
Project-URL: Issue Tracker, https://github.com/Dennis-van-Gils/python-dvg-pyqtgraph-threadsafe/issues
Keywords: ring buffer,circular buffer,pyqtgraph,thread safe,chart,plot
Classifier: Development Status :: 5 - Production/Stable
Classifier: License :: OSI Approved :: MIT License
Classifier: Intended Audience :: Developers
Classifier: Intended Audience :: Science/Research
Classifier: Operating System :: OS Independent
Classifier: Programming Language :: Python
Classifier: Programming Language :: Python :: 3
Classifier: Topic :: Multimedia :: Graphics
Classifier: Topic :: Scientific/Engineering 
Classifier: Topic :: Scientific/Engineering :: Electronic Design Automation (EDA)
Classifier: Topic :: Scientific/Engineering :: Physics
Classifier: Topic :: Scientific/Engineering :: Visualization
Requires-Python: >=3.6
License-File: LICENSE.txt
License-File: AUTHORS.rst
Requires-Dist: typing-extensions
Requires-Dist: numpy <3.0,>=1.15
Requires-Dist: pyqtgraph ~=0.11
Requires-Dist: dvg-ringbuffer ~=1.1
Requires-Dist: qtpy
